fastapi_crawler_scheduler/__init__.py
fastapi_crawler_scheduler/service/__init__.py
fastapi_crawler_scheduler/service/baseScheduler.py
fastapi_crawler_scheduler/service/dbRedisHelper.py
fastapi_crawler_scheduler/service/taskService.py
fastapi_crawler_scheduler/utils/__init__.py
fastapi_crawler_scheduler/utils/exception.py
fastapi_crawler_scheduler-2.1.5.dist-info/METADATA
fastapi_crawler_scheduler-2.1.5.dist-info/WHEEL
fastapi_crawler_scheduler-2.1.5.dist-info/RECORD
