Metadata-Version: 2.1
Name: fastapi-crawler-scheduler
Version: 2.1.5
Summary: 删除多余代码
Author: laowang
Author-email: 847063657@qq.com
Requires-Python: >=3.7,<4.0
Classifier: Programming Language :: Python :: 3
Classifier: Programming Language :: Python :: 3.7
Classifier: Programming Language :: Python :: 3.8
Classifier: Programming Language :: Python :: 3.9
Classifier: Programming Language :: Python :: 3.10
Classifier: Programming Language :: Python :: 3.11
Classifier: Programming Language :: Python :: 3.12
Requires-Dist: APScheduler (>=3.9.1,<4.0.0)
Requires-Dist: fastapi (>=0.85.0,<0.86.0)
Requires-Dist: fastapi-utils (>=0.2.1,<0.3.0)
Requires-Dist: redis (>=4.3.4,<5.0.0)
Requires-Dist: uhashring (>=2.1,<3.0)
